mcp_tools/__init__.py
mcp_tools/__main__.py
mcp_tools/server copy.py
mcp_tools/server.py
swapnil_mcp_server-6.2.8.dist-info/licenses/LICENSE
swapnil_mcp_server-6.2.8.dist-info/METADATA
swapnil_mcp_server-6.2.8.dist-info/WHEEL
swapnil_mcp_server-6.2.8.dist-info/entry_points.txt
swapnil_mcp_server-6.2.8.dist-info/top_level.txt
swapnil_mcp_server-6.2.8.dist-info/RECORD
