Metadata-Version: 2.4
Name: swapnil-mcp-server
Version: 6.2.8
Summary: Model Context Protocol (MCP) server providing integrated tools for Microsoft Office and Microsoft Visual Studio Team Foundation Server automation. Features include Outlook Calendar meeting scheduling, TFS repository management with commit history tracking, and OpenWeatherMap-based weather information retrieval.
Author-email: swapnil dagade <swapnildagade@gmail.com>
License: MIT
Project-URL: Homepage, https://github.com/swapnildagade/swapnil-mcp-server
Project-URL: Bug Tracker, https://github.com/swapnildagade/swapnil-mcp-server/issues
Project-URL: Documentation, https://github.com/swapnildagade/swapnil-mcp-server#readme
Keywords: mcp,model-context-protocol,outlook,calendar,meeting,scheduling,automation,microsoft-outlook
Classifier: Programming Language :: Python :: 3
Classifier: License :: OSI Approved :: MIT License
Classifier: Operating System :: OS Independent
Classifier: Development Status :: 5 - Production/Stable
Classifier: Intended Audience :: Developers
Classifier: Topic :: Office/Business :: Scheduling
Classifier: Topic :: Communications :: Conferencing
Classifier: Environment :: Win32 (MS Windows)
Classifier: Intended Audience :: Information Technology
Classifier: Topic :: Software Development :: Libraries :: Python Modules
Requires-Python: >=3.9
License-File: LICENSE
Requires-Dist: mcp>=1.2.0
Requires-Dist: pywin32>=223
Requires-Dist: datetime
Requires-Dist: requests
Requires-Dist: urllib3
Dynamic: license-file
